[
    {
        "title": "Drucksysteme f\u00fcr die Landesfinanzschule Bayern\nOffenes Verfahren",
        "link": null
    },
    {
        "title": "Erneuerung Faulschlammablaufleitungen Kollektor 2\n\u00d6ffentliche Ausschreibung",
        "link": null
    },
    {
        "title": "L\u00f6schgruppenfahrzeug LF 10\nOffenes Verfahren",
        "link": null
    },
    {
        "title": "Mobiles Abgasmesssystem\n\u00d6ffentliche Ausschreibung",
        "link": null
    },
    {
        "title": "Neubau Turnhalle mit Hort - Estricharbeiten\n\u00d6ffentliche Ausschreibung",
        "link": null
    },
    {
        "title": "Pommernstr. 10 - Neubau Schulzentrum S\u00fcdwest / 2.BA - B3.2401 Betonwerksteinarbeiten\nOffenes Verfahren",
        "link": null
    },
    {
        "title": "Reparatur von Wildsch\u00e4den auf landwirtschaftlichen Fl\u00e4chen\n\u00d6ffentliche Ausschreibung",
        "link": null
    },
    {
        "title": "Revierkontrolldienst f\u00fcr die Residenz Ellingen\n\u00d6ffentliche Ausschreibung",
        "link": null
    },
    {
        "title": "AmperVerband Kl\u00e4ranlage - Lieferung und Einsatzoptimierung von polymeren Flockungsmitteln\nOffenes Verfahren",
        "link": null
    },
    {
        "title": "Beschaffung von Berufs- und Arbeitskleidung im Mietservice f\u00fcr die Gro\u00dfe Kreisstadt N\u00f6rdlingen\nOffenes Verfahren",
        "link": null
    },
    {
        "title": "Containergestellung, Einsammeln, Verpressen, Verladen und Transport von Kartonagen\nOffenes Verfahren",
        "link": null
    },
    {
        "title": "Containergestellung, Einsammeln, Verpressen, Verladen und Transport von Kartonagen\nOffenes Verfahren",
        "link": null
    },
    {
        "title": "Containergestellung, Einsammeln, Verpressen, Verladen und Transport von Kartonagen\nOffenes Verfahren",
        "link": null
    },
    {
        "title": "Containergestellung, Einsammeln, Verpressen, Verladen und Transport von Kartonagen\nOffenes Verfahren",
        "link": null
    },
    {
        "title": "Containergestellung, Einsammeln, Verpressen, Verladen und Transport von Kartonagen\nOffenes Verfahren",
        "link": null
    },
    {
        "title": "Containergestellung, Einsammeln, Verpressen, Verladen und Transport von Kartonagen\nOffenes Verfahren",
        "link": null
    },
    {
        "title": "Containergestellung, Einsammeln, Verpressen, Verladen und Transport von Kartonagen\nOffenes Verfahren",
        "link": null
    },
    {
        "title": "Containergestellung, Einsammeln, Verpressen, Verladen und Transport von Kartonagen\nOffenes Verfahren",
        "link": null
    },
    {
        "title": "Containergestellung, Einsammeln, Verpressen, Verladen und Transport von Kartonagen\nOffenes Verfahren",
        "link": null
    },
    {
        "title": "Containergestellung, Einsammeln, Verpressen, Verladen und Transport von Kartonagen\nOffenes Verfahren",
        "link": null
    },
    {
        "title": "Containergestellung, Einsammeln, Verpressen, Verladen und Transport von Kartonagen\nOffenes Verfahren",
        "link": null
    },
    {
        "title": "Containergestellung, Einsammeln, Verpressen, Verladen und Transport von Kartonagen\nOffenes Verfahren",
        "link": null
    },
    {
        "title": "Containergestellung, Einsammeln, Verpressen, Verladen und Transport von Kartonagen\nOffenes Verfahren",
        "link": null
    },
    {
        "title": "Containergestellung, Einsammeln, Verpressen, Verladen und Transport von Kartonagen\nOffenes Verfahren",
        "link": null
    },
    {
        "title": "Containergestellung, Einsammeln, Verpressen, Verladen und Transport von Kartonagen\nOffenes Verfahren",
        "link": null
    }
]