[
    {
        "title": "Ausstattungs- und Einrichtungsgegenst\u00e4nde f\u00fcr die AnkER-Einrichtung Deggendorf\nOffenes Verfahren",
        "link": null
    },
    {
        "title": "Auswahlverfahren Sulzthal - Gigabit-RL 2.0 (LSP)\nVerhandlungsverfahren mit Teilnahmewettbewerb (Teil 1)",
        "link": null
    },
    {
        "title": "Dienstleistungsunterst\u00fctzung f\u00fcr das Projekt NEPTUN RZ (BayLfSt)\nOffenes Verfahren",
        "link": null
    },
    {
        "title": "Elementaranalysator f\u00fcr die CHNSO\n\u00d6ffentliche Ausschreibung",
        "link": null
    },
    {
        "title": "HAS+ VP306 Fassade WDVS\nOffenes Verfahren",
        "link": null
    },
    {
        "title": "Sicherheitsdienst f\u00fcr die Rathausgeb\u00e4ude und das Jugendamt der Stadt Landshut\n\u00d6ffentliche Ausschreibung",
        "link": null
    },
    {
        "title": "Technische Gase 2026-2029\nOffenes Verfahren",
        "link": null
    },
    {
        "title": "Unterhaltsreinigung f\u00fcr die Geb\u00e4ude des Rathauses 2 der Stadt Landshut\nOffenes Verfahren",
        "link": null
    },
    {
        "title": "Wartungsvertrag BHKW-Anlage f\u00fcr Bamberg Service/Kl\u00e4ranlage\nOffenes Verfahren",
        "link": null
    },
    {
        "title": "A2 - H\u00e4ngekrananlage KBK\n\u00d6ffentliche Ausschreibung",
        "link": null
    },
    {
        "title": "Beschaffung von Schul-IT Leistungen f\u00fcr die Katholische Jugendf\u00fcrsorge der Di\u00f6zese Regensburg\nOffenes Verfahren",
        "link": null
    },
    {
        "title": "CTD.QMAT26\nOffenes Verfahren",
        "link": null
    },
    {
        "title": "Ersatzbeschaffung eines Tankl\u00f6schfahrzeugs (TLF) 3000 mit Staffelkabine f\u00fcr die FFW Hochbr\u00fcck\nOffenes Verfahren",
        "link": null
    },
    {
        "title": "Europaweite Ausschreibung Facility Services Geb\u00e4ude ZMPT\nOffenes Verfahren",
        "link": null
    },
    {
        "title": "F\u00fcrther Tor, Neubau KiTa, Dachdeckungsarbeiten\n\u00d6ffentliche Ausschreibung",
        "link": null
    },
    {
        "title": "Laborleistungen\nVerhandlungsverfahren mit Teilnahmewettbewerb (Teil 1)",
        "link": null
    },
    {
        "title": "Neubau einer Mensa in Holz-Hybridbauweise mit multifunktionaler Nutzung und Tiefgarage - MSR-Technik\nOffenes Verfahren",
        "link": null
    },
    {
        "title": "Personenbef\u00f6rderungsleistungen im Linienverkehr auf der Linie Garmisch-Partenkirchen \u2013 Grainau - Eib\nOffenes Verfahren",
        "link": null
    },
    {
        "title": "Schachterneuerung Willstra\u00dfe\n\u00d6ffentliche Ausschreibung",
        "link": null
    },
    {
        "title": "Umbau und Erweiterung der Montessori-Schule - TGA-Fachplanung ELT + FT (ALG 4-6) - LPH 1-9\nVerhandlungsverfahren mit Teilnahmewettbewerb (Teil 1)",
        "link": null
    },
    {
        "title": "Unterhalts- und Glasreinigung PI Plattling\n\u00d6ffentliche Ausschreibung",
        "link": null
    },
    {
        "title": "Warm- / Kaltspeisenbelieferung f\u00fcr 4 Kindertagesst\u00e4tten der Markt Gemeinde Garmisch-Partenkirchen\nOffenes Verfahren",
        "link": null
    },
    {
        "title": "Ausbau der M\u00fchlpoint- und Rothenpointstra\u00dfe im Ortsteil M\u00fchlst\u00e4tt/ Gemeinde Schechen\n\u00d6ffentliche Ausschreibung",
        "link": null
    },
    {
        "title": "Besuchermodellierung\n\u00d6ffentliche Ausschreibung",
        "link": null
    },
    {
        "title": "Erneuerung Stromversorgung (3. UG-Paket 1)\n\u00d6ffentliche Ausschreibung",
        "link": null
    }
]